packagekit/__init__.py
packagekit-0.1.0.dist-info/METADATA
packagekit-0.1.0.dist-info/WHEEL
packagekit-0.1.0.dist-info/RECORD
